recurrence_popover/__init__.py
recurrence_popover/recurrence_popover.glade
recurrence_popover/recurrence_popover.py
recurrence_popover/tests/__init__.py
recurrence_popover/tests/manual_test.py
gtk_recurrence_popover-5.0.0.dist-info/WHEEL
gtk_recurrence_popover-5.0.0.dist-info/METADATA
gtk_recurrence_popover-5.0.0.dist-info/RECORD
